LICENSE
MANIFEST.in
README.md
README.txt
pyproject.toml
setup.cfg
setup.py
pohmm/__init__.py
pohmm/_hmmc.c
pohmm/_hmmc.pyx
pohmm/classification.py
pohmm/pohmm.py
pohmm/utils.py
pohmm/version.py
pohmm.egg-info/PKG-INFO
pohmm.egg-info/SOURCES.txt
pohmm.egg-info/dependency_links.txt
pohmm.egg-info/requires.txt
pohmm.egg-info/top_level.txt
pohmm/../LICENSE
pohmm/../MANIFEST.in
pohmm/../README.md
pohmm/../README.txt
pohmm/tests/__main__.py
pohmm/tests/conftest.py
pohmm/tests/test_examples.py
pohmm/tests/test_utils.py