Metadata-Version: 2.1
Name: pohmm
Version: 0.5
Summary: Partially observable hidden Markov model
Home-page: https://github.com/vmonaco/pohmm
Author: Vinnie Monaco
Author-email: contact@vmonaco.com
License: MIT
Keywords: hidden Markov model data analysis
Platform: UNKNOWN
Classifier: Development Status :: 2 - Pre-Alpha
Classifier: License :: OSI Approved
Classifier: Intended Audience :: Developers
Classifier: Intended Audience :: Science/Research
Classifier: Topic :: Software Development
Classifier: Topic :: Scientific/Engineering
Classifier: Programming Language :: Cython
Classifier: Programming Language :: Python
Classifier: Programming Language :: Python :: 3
Classifier: Programming Language :: Python :: 3.3
Classifier: Programming Language :: Python :: 3.4
Classifier: Programming Language :: Python :: 3.5
Classifier: Programming Language :: Python :: 3.6
Provides-Extra: testing
Provides-Extra: docs
